shapeletpy/ShapeletClassifier.py
shapeletpy/__init__.py.py
shapeletpy-0.9.2.dist-info/LICENSE
shapeletpy-0.9.2.dist-info/METADATA
shapeletpy-0.9.2.dist-info/WHEEL
shapeletpy-0.9.2.dist-info/top_level.txt
shapeletpy-0.9.2.dist-info/RECORD
