Metadata-Version: 2.1
Name: shapeletpy
Version: 0.9.2
Summary: Time series classification Using Shapelets
Home-page: https://github.com/rohitvincent/shapeletpy
Author: Rohit Vincent
Author-email: rohit.vincent@ucdconnect.ie
License: MIT
Platform: UNKNOWN
